estndv/__init__.py
estndv/estimate.py
estndv/model_paras.npy
estndv-0.0.2.dist-info/LICENSE
estndv-0.0.2.dist-info/METADATA
estndv-0.0.2.dist-info/WHEEL
estndv-0.0.2.dist-info/top_level.txt
estndv-0.0.2.dist-info/RECORD
