Metadata-Version: 2.1
Name: estndv
Version: 0.0.2
Summary: Learned sample-based estimator for number of distinct values.
Home-page: https://github.com/wurenzhi/learned_ndv_estimator
Author: Renzhi Wu
Author-email: renzhiwu@gatech.edu
License: UNKNOWN
Project-URL: Bug Tracker, https://github.com/wurenzhi/learned_ndv_estimator/issues
Platform: UNKNOWN
Classifier: Programming Language :: Python :: 3
Classifier: License :: OSI Approved :: MIT License
Classifier: Operating System :: OS Independent
Requires-Python: >=3.6
License-File: LICENSE
Requires-Dist: numpy
